{
    "paging": {
        "cursors": {
            "after": "WTI5dGJXVnVkRjlqZAFhKemIzSTZANVGd5T0RZAMU9USTBNRGMwTlRRek1qb3hORGd5TmpBeU56azUZD", 
            "before": "WTI5dGJXVnVkRjlqZAFhKemIzSTZANVGd5T0RReE9UWTJOREV3TWpjeU16b3hORGd5TlRZAeE9EYzEZD"
        }
    }, 
    "data": [
        {
            "from": {
                "name": "Andy Zhang", 
                "id": "489084884566575"
            }, 
            "message_tags": [
                {
                    "length": 5, 
                    "offset": 3, 
                    "type": "user", 
                    "id": "329611890539313", 
                    "name": "Nadir Akhtar"
                }
            ], 
            "like_count": 3, 
            "can_remove": false, 
            "created_time": "2016-12-24T06:44:35+0000", 
            "message": "Hi Nadir", 
            "id": "1828419664102723", 
            "user_likes": false
        }, 
        {
            "from": {
                "name": "Iris Tong", 
                "id": "10207270502903970"
            }, 
            "message_tags": [
                {
                    "length": 5, 
                    "offset": 3, 
                    "type": "user", 
                    "id": "329611890539313", 
                    "name": "Nadir Akhtar"
                }
            ], 
            "like_count": 2, 
            "can_remove": false, 
            "created_time": "2016-12-24T07:01:42+0000", 
            "message": "Hi Nadir", 
            "id": "1828424517435571", 
            "user_likes": false
        }, 
        {
            "from": {
                "name": "Nadir Akhtar", 
                "id": "329611890539313"
            }, 
            "like_count": 1, 
            "can_remove": false, 
            "created_time": "2016-12-24T09:45:54+0000", 
            "message": "Wait but why", 
            "id": "1828475184097171", 
            "user_likes": false
        }, 
        {
            "from": {
                "name": "Claire Lee", 
                "id": "10154906636620585"
            }, 
            "like_count": 0, 
            "can_remove": false, 
            "created_time": "2016-12-24T09:49:53+0000", 
            "message": "please vote for 3 midterm option i don't want to take a final", 
            "id": "1828476694097020", 
            "user_likes": false
        }, 
        {
            "from": {
                "name": "Jong Choi", 
                "id": "10202916034040631"
            }, 
            "like_count": 5, 
            "can_remove": false, 
            "created_time": "2016-12-24T11:06:09+0000", 
            "message": "PLEASE VOTE FOR 3 MIDTERM PLEASE", 
            "id": "1828501864094503", 
            "user_likes": false
        }, 
        {
            "from": {
                "name": "Fahad Kamran", 
                "id": "853762824638415"
            }, 
            "message_tags": [
                {
                    "length": 11, 
                    "offset": 0, 
                    "type": "user", 
                    "id": "10204862288826852", 
                    "name": "Mike Aboody"
                }
            ], 
            "like_count": 0, 
            "can_remove": false, 
            "created_time": "2016-12-24T12:00:00+0000", 
            "message": "Mike Aboody", 
            "id": "1828516734093016", 
            "user_likes": false
        }, 
        {
            "from": {
                "name": "Emma Jaeger", 
                "id": "1018048494916024"
            }, 
            "message_tags": [
                {
                    "length": 9, 
                    "offset": 0, 
                    "type": "user", 
                    "id": "10201672167921800", 
                    "name": "Matt Owen"
                }
            ], 
            "like_count": 1, 
            "can_remove": false, 
            "created_time": "2016-12-24T18:06:39+0000", 
            "message": "Matt Owen", 
            "id": "1828659240745432", 
            "user_likes": false
        }
    ]
}