{
    "paging": {
        "cursors": {
            "after": "WTI5dGJXVnVkRjlqZAFhKemIzSTZANVGd6TWpJMk9EQTJOekExTVRJeE5qb3hORGd6TWpJNE5UTXgZD", 
            "before": "WTI5dGJXVnVkRjlqZAFhKemIzSTZANVGd6TVRFME1Ua3lNRFE1TnpFMk5Eb3hORGd6TURVd09ESTAZD"
        }
    }, 
    "data": [
        {
            "from": {
                "name": "Vanessa Travieso", 
                "id": "878785212133369"
            }, 
            "like_count": 4, 
            "can_remove": false, 
            "created_time": "2016-12-29T22:33:44+0000", 
            "message": "i cant handle this paul \ud83d\ude02", 
            "id": "1831141920497164", 
            "user_likes": false
        }, 
        {
            "from": {
                "name": "Aj Albaaj", 
                "id": "10201965267368177"
            }, 
            "like_count": 2, 
            "can_remove": false, 
            "created_time": "2016-12-29T22:44:04+0000", 
            "message": "Sad reacts only", 
            "id": "1831144550496901", 
            "user_likes": false
        }, 
        {
            "from": {
                "name": "Abrar Haque", 
                "id": "882261618451884"
            }, 
            "message_tags": [
                {
                    "length": 12, 
                    "offset": 0, 
                    "type": "user", 
                    "id": "10202646460382830", 
                    "name": "Daniel Saedi"
                }
            ], 
            "like_count": 3, 
            "can_remove": false, 
            "created_time": "2016-12-29T22:45:20+0000", 
            "message": "Daniel Saedi", 
            "id": "1831146103830079", 
            "user_likes": false
        }, 
        {
            "from": {
                "name": "Monica Lin", 
                "id": "395182924009980"
            }, 
            "message_tags": [
                {
                    "length": 12, 
                    "offset": 0, 
                    "type": "user", 
                    "id": "1718630648466565", 
                    "name": "Rachelle Jin"
                }
            ], 
            "like_count": 0, 
            "can_remove": false, 
            "created_time": "2016-12-29T22:48:11+0000", 
            "message": "Rachelle Jin", 
            "id": "1831146833830006", 
            "user_likes": false
        }, 
        {
            "from": {
                "name": "Dechen Bosiljevac", 
                "id": "184618805265418"
            }, 
            "message_tags": [
                {
                    "length": 9, 
                    "offset": 0, 
                    "type": "user", 
                    "id": "10153700857588567", 
                    "name": "Avery Yip"
                }
            ], 
            "like_count": 0, 
            "can_remove": false, 
            "created_time": "2016-12-29T23:10:46+0000", 
            "message": "Avery Yip", 
            "id": "1831155663829123", 
            "user_likes": false
        }, 
        {
            "from": {
                "name": "Melissa Ly", 
                "id": "823682560978078"
            }, 
            "message_tags": [
                {
                    "length": 8, 
                    "offset": 0, 
                    "type": "user", 
                    "id": "882959285048163", 
                    "name": "Andre He"
                }, 
                {
                    "length": 14, 
                    "offset": 9, 
                    "type": "user", 
                    "id": "125072091177814", 
                    "name": "Jose Jasso Jr."
                }
            ], 
            "like_count": 1, 
            "can_remove": false, 
            "created_time": "2016-12-29T23:13:11+0000", 
            "message": "Andre He Jose Jasso Jr. 10/10", 
            "id": "1831156190495737", 
            "user_likes": false
        }, 
        {
            "from": {
                "name": "Alejandro Bolanos", 
                "id": "10206816614768044"
            }, 
            "message_tags": [
                {
                    "length": 14, 
                    "offset": 0, 
                    "type": "user", 
                    "id": "665471566890598", 
                    "name": "Everett Fisher"
                }
            ], 
            "like_count": 1, 
            "can_remove": false, 
            "created_time": "2016-12-29T23:18:51+0000", 
            "message": "Everett Fisher omg hit me right in the feels", 
            "id": "1831158230495533", 
            "user_likes": false
        }, 
        {
            "from": {
                "name": "Karen Liou", 
                "id": "764059467019803"
            }, 
            "message_tags": [
                {
                    "length": 9, 
                    "offset": 0, 
                    "type": "user", 
                    "id": "720551814689842", 
                    "name": "Jose Lynn"
                }, 
                {
                    "length": 17, 
                    "offset": 10, 
                    "type": "user", 
                    "id": "744484392311454", 
                    "name": "Sherman Ultrasoft"
                }
            ], 
            "like_count": 0, 
            "can_remove": false, 
            "created_time": "2016-12-29T23:23:15+0000", 
            "message": "Jose Lynn Sherman Ultrasoft OMG", 
            "id": "1831159353828754", 
            "user_likes": false
        }, 
        {
            "from": {
                "name": "Nick Pingitore", 
                "id": "1584046021815433"
            }, 
            "message_tags": [
                {
                    "length": 20, 
                    "offset": 0, 
                    "type": "user", 
                    "id": "4142929989637", 
                    "name": "Paul Poghos Iskajyan"
                }
            ], 
            "like_count": 1, 
            "can_remove": false, 
            "created_time": "2016-12-30T00:08:18+0000", 
            "message": "Paul Poghos Iskajyan u took the spaces joke but overall 9.78/10", 
            "id": "1831171273827562", 
            "user_likes": false
        }, 
        {
            "from": {
                "name": "Julia Morris", 
                "id": "10201425361954880"
            }, 
            "message_tags": [
                {
                    "length": 12, 
                    "offset": 0, 
                    "type": "user", 
                    "id": "684837554906360", 
                    "name": "Danny Miller"
                }
            ], 
            "like_count": 1, 
            "can_remove": false, 
            "created_time": "2016-12-30T00:21:59+0000", 
            "message": "Danny Miller watch this", 
            "id": "1831175550493801", 
            "user_likes": false
        }, 
        {
            "from": {
                "name": "Jason Tang", 
                "id": "10203284383523760"
            }, 
            "message_tags": [
                {
                    "length": 11, 
                    "offset": 0, 
                    "type": "user", 
                    "id": "10202433519981882", 
                    "name": "Andrew Wang"
                }
            ], 
            "like_count": 2, 
            "can_remove": false, 
            "created_time": "2016-12-30T01:08:26+0000", 
            "message": "Andrew Wang watcj", 
            "id": "1831185017159521", 
            "user_likes": false
        }, 
        {
            "from": {
                "name": "Viraj Telang", 
                "id": "10152351154588127"
            }, 
            "message_tags": [
                {
                    "length": 6, 
                    "offset": 0, 
                    "type": "user", 
                    "id": "881209201892041", 
                    "name": "Robert Xu"
                }
            ], 
            "like_count": 0, 
            "can_remove": false, 
            "created_time": "2016-12-30T01:31:16+0000", 
            "message": "Robert lmao they have you in this seeking Alpha. Gonna miss you in 2017", 
            "id": "1831190090492347", 
            "user_likes": false
        }, 
        {
            "from": {
                "name": "Arun Sundar", 
                "id": "10204874877303922"
            }, 
            "message_tags": [
                {
                    "length": 4, 
                    "offset": 0, 
                    "type": "user", 
                    "id": "4142929989637", 
                    "name": "Paul Poghos Iskajyan"
                }
            ], 
            "like_count": 1, 
            "can_remove": false, 
            "created_time": "2016-12-30T01:35:51+0000", 
            "message": "Paul this is true beauty", 
            "id": "1831191843825505", 
            "user_likes": false
        }, 
        {
            "from": {
                "name": "Sean Guo", 
                "id": "949791635039874"
            }, 
            "message_tags": [
                {
                    "length": 7, 
                    "offset": 0, 
                    "type": "user", 
                    "id": "10206609614625855", 
                    "name": "Amy Lin"
                }
            ], 
            "like_count": 1, 
            "can_remove": false, 
            "created_time": "2016-12-30T01:36:27+0000", 
            "message": "Amy Lin", 
            "id": "1831191937158829", 
            "user_likes": false
        }, 
        {
            "from": {
                "name": "Danielle Hilborn", 
                "id": "973871849295276"
            }, 
            "message_tags": [
                {
                    "length": 4, 
                    "offset": 0, 
                    "type": "user", 
                    "id": "10202806713075553", 
                    "name": "Nada Al-Alusi"
                }, 
                {
                    "length": 6, 
                    "offset": 5, 
                    "type": "user", 
                    "id": "745587202173647", 
                    "name": "Fatima Atty Ibrahim"
                }
            ], 
            "like_count": 1, 
            "can_remove": false, 
            "created_time": "2016-12-30T01:45:54+0000", 
            "message": "Nada Fatima", 
            "id": "1831194717158551", 
            "user_likes": false
        }, 
        {
            "from": {
                "name": "Olivia Fang", 
                "id": "659304657499737"
            }, 
            "message_tags": [
                {
                    "length": 13, 
                    "offset": 0, 
                    "type": "user", 
                    "id": "922394724439009", 
                    "name": "Katrina Jiang"
                }
            ], 
            "like_count": 0, 
            "can_remove": false, 
            "created_time": "2016-12-30T01:51:04+0000", 
            "message": "Katrina Jiang", 
            "id": "1831197083824981", 
            "user_likes": false
        }, 
        {
            "from": {
                "name": "Ana Lagunas", 
                "id": "10152896636008208"
            }, 
            "message_tags": [
                {
                    "length": 17, 
                    "offset": 0, 
                    "type": "user", 
                    "id": "558099110983020", 
                    "name": "Vanessa Sarmiento"
                }, 
                {
                    "length": 13, 
                    "offset": 18, 
                    "type": "user", 
                    "id": "689516567774533", 
                    "name": "Clara Ram\u00edrez"
                }
            ], 
            "like_count": 1, 
            "can_remove": false, 
            "created_time": "2016-12-30T01:53:52+0000", 
            "message": "Vanessa Sarmiento Clara Ram\u00edrez", 
            "id": "1831198987158124", 
            "user_likes": false
        }, 
        {
            "from": {
                "name": "Daisy Wu", 
                "id": "10152431909337628"
            }, 
            "message_tags": [
                {
                    "length": 12, 
                    "offset": 0, 
                    "type": "user", 
                    "id": "339344082907993", 
                    "name": "Trevor Laity"
                }
            ], 
            "like_count": 0, 
            "can_remove": false, 
            "created_time": "2016-12-30T03:00:04+0000", 
            "message": "Trevor Laity", 
            "id": "1831239840487372", 
            "user_likes": false
        }, 
        {
            "from": {
                "name": "Alyzza Acacio", 
                "id": "10204904044415336"
            }, 
            "message_tags": [
                {
                    "length": 7, 
                    "offset": 0, 
                    "type": "user", 
                    "id": "10204554305005862", 
                    "name": "Yumi Ko"
                }
            ], 
            "like_count": 0, 
            "can_remove": false, 
            "created_time": "2016-12-30T05:20:19+0000", 
            "message": "Yumi Ko", 
            "id": "1831279167150106", 
            "user_likes": false
        }, 
        {
            "from": {
                "name": "Garima Raheja", 
                "id": "1511429412412259"
            }, 
            "message_tags": [
                {
                    "length": 7, 
                    "offset": 0, 
                    "type": "user", 
                    "id": "442539502621270", 
                    "name": "Roy Kim"
                }
            ], 
            "like_count": 2, 
            "can_remove": false, 
            "created_time": "2016-12-30T05:49:37+0000", 
            "message": "Roy Kim 1:34 \"our shit\"", 
            "id": "1831287283815961", 
            "user_likes": false
        }, 
        {
            "from": {
                "name": "Miguel Sanchez", 
                "id": "1067967629908250"
            }, 
            "message_tags": [
                {
                    "length": 12, 
                    "offset": 0, 
                    "type": "user", 
                    "id": "1079487612077188", 
                    "name": "Jonathan Gao"
                }, 
                {
                    "length": 10, 
                    "offset": 13, 
                    "type": "user", 
                    "id": "1574107706141074", 
                    "name": "Kevin Wang"
                }, 
                {
                    "length": 12, 
                    "offset": 24, 
                    "type": "user", 
                    "id": "829020627184990", 
                    "name": "Casey Denton"
                }
            ], 
            "like_count": 2, 
            "can_remove": false, 
            "created_time": "2016-12-30T07:25:33+0000", 
            "message": "Jonathan Gao Kevin Wang Casey Denton", 
            "id": "1831314447146578", 
            "user_likes": false
        }, 
        {
            "from": {
                "name": "Lindsay Garner", 
                "id": "10202294366629363"
            }, 
            "message_tags": [
                {
                    "length": 11, 
                    "offset": 0, 
                    "type": "user", 
                    "id": "807560632608874", 
                    "name": "Patty Reddi"
                }
            ], 
            "like_count": 1, 
            "can_remove": false, 
            "created_time": "2016-12-30T16:05:39+0000", 
            "message": "Patty Reddi", 
            "id": "1831522643792425", 
            "user_likes": false
        }, 
        {
            "from": {
                "name": "Lizzy Goldstein", 
                "id": "10201737241831431"
            }, 
            "message_tags": [
                {
                    "length": 13, 
                    "offset": 0, 
                    "type": "user", 
                    "id": "1641848972704968", 
                    "name": "Hannah Brandt"
                }, 
                {
                    "length": 15, 
                    "offset": 14, 
                    "type": "user", 
                    "id": "824821294206714", 
                    "name": "Hannah Schwartz"
                }, 
                {
                    "length": 19, 
                    "offset": 30, 
                    "type": "user", 
                    "id": "10204060985303488", 
                    "name": "Harley J Williamson"
                }, 
                {
                    "length": 18, 
                    "offset": 50, 
                    "type": "user", 
                    "id": "459611354177761", 
                    "name": "Isabel De los Rios"
                }, 
                {
                    "length": 20, 
                    "offset": 69, 
                    "type": "user", 
                    "id": "10204661242241312", 
                    "name": "Margo van den Helder"
                }, 
                {
                    "length": 11, 
                    "offset": 90, 
                    "type": "user", 
                    "id": "496908207076547", 
                    "name": "Shelby Will"
                }, 
                {
                    "length": 17, 
                    "offset": 102, 
                    "type": "user", 
                    "id": "884053374941317", 
                    "name": "Alyssa Gerontides"
                }
            ], 
            "like_count": 3, 
            "can_remove": false, 
            "created_time": "2016-12-30T19:01:42+0000", 
            "message": "Hannah Brandt Hannah Schwartz Harley J Williamson Isabel De los Rios Margo van den Helder Shelby Will Alyssa Gerontides", 
            "id": "1831593140452042", 
            "user_likes": false
        }, 
        {
            "from": {
                "name": "Michael Ershov", 
                "id": "4155002210789"
            }, 
            "message_tags": [
                {
                    "length": 15, 
                    "offset": 0, 
                    "type": "user", 
                    "id": "929603527068276", 
                    "name": "Kanami Kitagawa"
                }, 
                {
                    "length": 10, 
                    "offset": 16, 
                    "type": "user", 
                    "id": "540391786099058", 
                    "name": "Ameryl Loi"
                }
            ], 
            "like_count": 0, 
            "can_remove": false, 
            "created_time": "2016-12-30T20:06:02+0000", 
            "message": "Kanami Kitagawa Ameryl Loi", 
            "id": "1831617660449590", 
            "user_likes": false
        }, 
        {
            "from": {
                "name": "Dana King", 
                "id": "10206049353620863"
            }, 
            "message_tags": [
                {
                    "length": 12, 
                    "offset": 0, 
                    "type": "user", 
                    "id": "223705964494294", 
                    "name": "Sierra Gomez"
                }
            ], 
            "like_count": 0, 
            "can_remove": false, 
            "created_time": "2016-12-30T20:48:17+0000", 
            "message": "Sierra Gomez too personal.", 
            "id": "1831629350448421", 
            "user_likes": false
        }, 
        {
            "from": {
                "name": "Joseph Hernandez", 
                "id": "151540031896925"
            }, 
            "message_tags": [
                {
                    "length": 18, 
                    "offset": 0, 
                    "type": "user", 
                    "id": "914068968614257", 
                    "name": "Sara Jennifer Zaat"
                }
            ], 
            "like_count": 0, 
            "can_remove": false, 
            "created_time": "2016-12-31T01:42:58+0000", 
            "message": "Sara Jennifer Zaat", 
            "id": "1831721520439204", 
            "user_likes": false
        }, 
        {
            "from": {
                "name": "Olivia Tandowsky", 
                "id": "787972547956730"
            }, 
            "message_tags": [
                {
                    "length": 12, 
                    "offset": 17, 
                    "type": "user", 
                    "id": "210437292746258", 
                    "name": "Roxy Shojaie"
                }, 
                {
                    "length": 20, 
                    "offset": 30, 
                    "type": "user", 
                    "id": "220091328397493", 
                    "name": "Katerina Schoenegger"
                }
            ], 
            "like_count": 2, 
            "can_remove": false, 
            "created_time": "2016-12-31T06:26:52+0000", 
            "message": "this is too much Roxy Shojaie Katerina Schoenegger", 
            "id": "1831827253761964", 
            "user_likes": false
        }, 
        {
            "from": {
                "name": "Daylen Yang", 
                "id": "4664525147396"
            }, 
            "message_tags": [
                {
                    "length": 12, 
                    "offset": 0, 
                    "type": "user", 
                    "id": "10203801953837689", 
                    "name": "Nathan Mandi"
                }
            ], 
            "like_count": 1, 
            "can_remove": false, 
            "created_time": "2016-12-31T09:06:29+0000", 
            "message": "Nathan Mandi 0:59", 
            "id": "1831868343757855", 
            "user_likes": false
        }, 
        {
            "from": {
                "name": "Diana Diaz Morales", 
                "id": "220413261727414"
            }, 
            "message_tags": [
                {
                    "length": 16, 
                    "offset": 0, 
                    "type": "user", 
                    "id": "739073359506928", 
                    "name": "Elixandro Orosco"
                }
            ], 
            "like_count": 1, 
            "can_remove": false, 
            "created_time": "2016-12-31T09:19:05+0000", 
            "message": "Elixandro Orosco watch this please \ud83d\ude02", 
            "id": "1831871147090908", 
            "user_likes": false
        }, 
        {
            "from": {
                "name": "Samantha Cristol", 
                "id": "10202054330347800"
            }, 
            "message_tags": [
                {
                    "length": 11, 
                    "offset": 0, 
                    "type": "user", 
                    "id": "10205575225043151", 
                    "name": "Dana Siegel"
                }
            ], 
            "like_count": 0, 
            "can_remove": false, 
            "created_time": "2016-12-31T18:10:16+0000", 
            "message": "Dana Siegel oh man", 
            "id": "1832134880397868", 
            "user_likes": false
        }, 
        {
            "from": {
                "name": "Jalyn Carpenter", 
                "id": "932695130076285"
            }, 
            "message_tags": [
                {
                    "length": 12, 
                    "offset": 0, 
                    "type": "user", 
                    "id": "10205525656849907", 
                    "name": "Mei Leieritz"
                }
            ], 
            "like_count": 0, 
            "can_remove": false, 
            "created_time": "2016-12-31T19:23:41+0000", 
            "message": "Mei Leieritz", 
            "id": "1832163880394968", 
            "user_likes": false
        }, 
        {
            "from": {
                "name": "Savannah Longoria", 
                "id": "1168941499788663"
            }, 
            "message_tags": [
                {
                    "length": 14, 
                    "offset": 0, 
                    "type": "user", 
                    "id": "10207556403977990", 
                    "name": "Tiffany Monroy"
                }
            ], 
            "like_count": 0, 
            "can_remove": false, 
            "created_time": "2016-12-31T23:55:31+0000", 
            "message": "Tiffany Monroy", 
            "id": "1832268067051216", 
            "user_likes": false
        }
    ]
}